{"cameraMode":{"drawMode":0,"name":"Shaded","section":"Shading Mode"},"sceneLighting":true,"audioPlay":false,"sceneViewState":{"m_AlwaysRefresh":false,"showFog":true,"showSkybox":true,"showFlares":true,"showImageEffects":true,"showParticleSystems":true,"showVisualEffectGraphs":true,"m_FxEnabled":true},"in2DMode":false,"pivot":{"x":19.027503967285158,"y":3.611598014831543,"z":-38.59973907470703},"rotation":{"x":-0.021041525527834894,"y":-0.9710044860839844,"z":0.2191746085882187,"w":-0.09321264177560806},"size":15.983363151550293,"orthographic":false}